prosperparser/__init__.py
prosperparser/_version.py
prosperparser/_version.pyi
prosperparser/cleave.py
prosperparser/cli.py
prosperparser/constants.py
prosperparser/parse.py
prosperparser/py.typed
prosperparser-0.2.1.dist-info/METADATA
prosperparser-0.2.1.dist-info/WHEEL
prosperparser-0.2.1.dist-info/entry_points.txt
prosperparser-0.2.1.dist-info/licenses/LICENSE
prosperparser-0.2.1.dist-info/RECORD
