Metadata-Version: 2.4
Name: prosperparser
Version: 0.2.1
Summary: A package for filtering the output of ProsperousPlus.
Project-URL: Homepage, https://github.com/theAeon/prosperparser
Project-URL: Bug Tracker, https://github.com/theAeon/prosperparser/issues
Project-URL: Discussions, https://github.com/theAeon/prosperparser/discussions
Project-URL: Changelog, https://github.com/theAeon/prosperparser/releases
Author-email: Andrew Robbins <robbiand@umich.edu>
License-Expression: MIT
License-File: LICENSE
Classifier: Development Status :: 1 - Planning
Classifier: Intended Audience :: Developers
Classifier: Intended Audience :: Science/Research
Classifier: Operating System :: OS Independent
Classifier: Programming Language :: Python
Classifier: Programming Language :: Python :: 3
Classifier: Programming Language :: Python :: 3 :: Only
Classifier: Programming Language :: Python :: 3.11
Classifier: Programming Language :: Python :: 3.12
Classifier: Programming Language :: Python :: 3.13
Classifier: Programming Language :: Python :: 3.14
Classifier: Topic :: Scientific/Engineering
Classifier: Typing :: Typed
Requires-Python: >=3.11
Requires-Dist: cappa>=0.31.0
Requires-Dist: pandas-stubs>=2.3.3.260113
Requires-Dist: pandas>=3
Requires-Dist: pyfastx>=2.3.0
